trino_connector/__init__.py
trino_connector/connector.py
trino_connector-0.1.0.dist-info/METADATA
trino_connector-0.1.0.dist-info/WHEEL
trino_connector-0.1.0.dist-info/top_level.txt
trino_connector-0.1.0.dist-info/RECORD
